heahmund/__init__.py
heahmund/http.py
heahmund/logger.py
heahmund/ping.py
heahmund/ssl.py
heahmund/status.py
heahmund/tcp.py
heahmund/udp.py
heahmund/utils.py
heahmund-0.1.2.dist-info/LICENSE.txt
heahmund-0.1.2.dist-info/METADATA
heahmund-0.1.2.dist-info/WHEEL
heahmund-0.1.2.dist-info/top_level.txt
heahmund-0.1.2.dist-info/RECORD
